adhanpy/PrayerTimes.py
adhanpy/__init__.py
adhanpy/astronomy/Astronomical.py
adhanpy/astronomy/CalendricalHelper.py
adhanpy/astronomy/SolarCoordinates.py
adhanpy/astronomy/SolarTime.py
adhanpy/astronomy/__init__.py
adhanpy/calculation/CalculationMethod.py
adhanpy/calculation/CalculationParameters.py
adhanpy/calculation/HighLatitudeRule.py
adhanpy/calculation/Madhab.py
adhanpy/calculation/MethodsParameters.py
adhanpy/calculation/PrayerAdjustments.py
adhanpy/calculation/Twilight.py
adhanpy/calculation/__init__.py
adhanpy/data/Coordinates.py
adhanpy/data/NightPortions.py
adhanpy/data/Prayer.py
adhanpy/data/ShadowLength.py
adhanpy/data/__init__.py
adhanpy/util/CalendarUtil.py
adhanpy/util/DateComponents.py
adhanpy/util/FloatUtil.py
adhanpy/util/TimeComponents.py
adhanpy/util/__init__.py
adhanpy-1.0.4.dist-info/LICENSE
adhanpy-1.0.4.dist-info/METADATA
adhanpy-1.0.4.dist-info/WHEEL
adhanpy-1.0.4.dist-info/top_level.txt
adhanpy-1.0.4.dist-info/RECORD
