Metadata-Version: 2.1
Name: adhanpy
Version: 1.0.4
Summary: An offline library calculating prayer times
Home-page: https://github.com/alphahm/adhanpy
Author: alphahm
Project-URL: Documentation, https://github.com/alphahm/adhanpy/blob/master/README.md
Project-URL: Changelog, https://github.com/alphahm/adhanpy/blob/master/CHANGES.md
Classifier: Operating System :: OS Independent
Classifier: Programming Language :: Python :: 3.9
Classifier: Programming Language :: Python :: 3.10
Classifier: Programming Language :: Python :: 3.11
Classifier: Programming Language :: Python :: 3.12
Classifier: License :: OSI Approved :: MIT License
Classifier: Operating System :: OS Independent
License-File: LICENSE
